[
  {
    "name": "Technology",
    "score": 27.066,
    "rankWonDb": 1,
    "diffD": 0,
    "diffW": 1,
    "diffM": null,
    "diffQ": null,
    "perf_week": 4.62,
    "perf_month": 10.69,
    "perf_quart": 23.36,
    "perf_half": 27.03,
    "perf_year": 50.89,
    "data": [
      {
        "date": "2026-05-26",
        "change": 1.69
      }
    ],
    "anl_datum": "2026-05-26T22:15:02.067Z"
  },
  {
    "name": "Energy",
    "score": 17.83,
    "rankWonDb": 2,
    "diffD": 0,
    "diffW": -1,
    "diffM": null,
    "diffQ": null,
    "perf_week": -4.2,
    "perf_month": 0.46,
    "perf_quart": 7.23,
    "perf_half": 30.54,
    "perf_year": 43.69,
    "data": [
      {
        "date": "2026-05-26",
        "change": -2.31
      }
    ],
    "anl_datum": "2026-05-26T22:15:02.067Z"
  },
  {
    "name": "Communication Services",
    "score": 15.520000000000001,
    "rankWonDb": 3,
    "diffD": 0,
    "diffW": 0,
    "diffM": null,
    "diffQ": null,
    "perf_week": -0.77,
    "perf_month": 4.33,
    "perf_quart": 10.43,
    "perf_half": 14.85,
    "perf_year": 37.56,
    "data": [
      {
        "date": "2026-05-26",
        "change": 1
      }
    ],
    "anl_datum": "2026-05-26T22:15:02.067Z"
  },
  {
    "name": "Basic Materials",
    "score": 13.486,
    "rankWonDb": 4,
    "diffD": 0,
    "diffW": 0,
    "diffM": null,
    "diffQ": null,
    "perf_week": 2.86,
    "perf_month": -0.67,
    "perf_quart": -6.13,
    "perf_half": 31.44,
    "perf_year": 48.92,
    "data": [
      {
        "date": "2026-05-26",
        "change": 2.49
      }
    ],
    "anl_datum": "2026-05-26T22:15:02.067Z"
  },
  {
    "name": "Industrials",
    "score": 10.928,
    "rankWonDb": 5,
    "diffD": 0,
    "diffW": 0,
    "diffM": null,
    "diffQ": null,
    "perf_week": 3.13,
    "perf_month": 1.84,
    "perf_quart": 0.17,
    "perf_half": 22.75,
    "perf_year": 29.71,
    "data": [
      {
        "date": "2026-05-26",
        "change": 1.94
      }
    ],
    "anl_datum": "2026-05-26T22:15:02.067Z"
  },
  {
    "name": "Real Estate",
    "score": 5.0920000000000005,
    "rankWonDb": 6,
    "diffD": 1,
    "diffW": 1,
    "diffM": null,
    "diffQ": null,
    "perf_week": 2.12,
    "perf_month": 1.62,
    "perf_quart": 1.74,
    "perf_half": 9.63,
    "perf_year": 10.73,
    "data": [
      {
        "date": "2026-05-26",
        "change": 0.48
      }
    ],
    "anl_datum": "2026-05-26T22:15:02.067Z"
  },
  {
    "name": "Financial",
    "score": 4.748,
    "rankWonDb": 7,
    "diffD": 1,
    "diffW": 1,
    "diffM": null,
    "diffQ": null,
    "perf_week": 1.3,
    "perf_month": 1.91,
    "perf_quart": 1.94,
    "perf_half": 6.31,
    "perf_year": 11.64,
    "data": [
      {
        "date": "2026-05-26",
        "change": 0.39
      }
    ],
    "anl_datum": "2026-05-26T22:15:02.067Z"
  },
  {
    "name": "Consumer Cyclical",
    "score": 4.602,
    "rankWonDb": 8,
    "diffD": -2,
    "diffW": 1,
    "diffM": null,
    "diffQ": null,
    "perf_week": 2.33,
    "perf_month": 0.63,
    "perf_quart": 2.49,
    "perf_half": 6.77,
    "perf_year": 10.63,
    "data": [
      {
        "date": "2026-05-26",
        "change": 0.35
      }
    ],
    "anl_datum": "2026-05-26T22:15:02.067Z"
  },
  {
    "name": "Utilities",
    "score": 2.646,
    "rankWonDb": 9,
    "diffD": 0,
    "diffW": 1,
    "diffM": null,
    "diffQ": null,
    "perf_week": 3.29,
    "perf_month": -2.67,
    "perf_quart": -3.51,
    "perf_half": 5.22,
    "perf_year": 17.7,
    "data": [
      {
        "date": "2026-05-26",
        "change": 0.39
      }
    ],
    "anl_datum": "2026-05-26T22:15:02.067Z"
  },
  {
    "name": "Healthcare",
    "score": 1.4399999999999997,
    "rankWonDb": 10,
    "diffD": 1,
    "diffW": 1,
    "diffM": null,
    "diffQ": null,
    "perf_week": 2.09,
    "perf_month": 2.15,
    "perf_quart": -5.27,
    "perf_half": -0.1,
    "perf_year": 15.69,
    "data": [
      {
        "date": "2026-05-26",
        "change": -0.64
      }
    ],
    "anl_datum": "2026-05-26T22:15:02.067Z"
  },
  {
    "name": "Consumer Defensive",
    "score": -0.02400000000000002,
    "rankWonDb": 11,
    "diffD": -1,
    "diffW": -5,
    "diffM": null,
    "diffQ": null,
    "perf_week": -3.95,
    "perf_month": -0.72,
    "perf_quart": -6.61,
    "perf_half": 8.8,
    "perf_year": 5.02,
    "data": [
      {
        "date": "2026-05-26",
        "change": -1.44
      }
    ],
    "anl_datum": "2026-05-26T22:15:02.067Z"
  }
]